thundersnow/__init__.py
thundersnow/compat.py
thundersnow/dateutil.py
thundersnow/fsutil.py
thundersnow/function.py
thundersnow/importutil.py
thundersnow/ioutil.py
thundersnow/memoize.py
thundersnow/optional.py
thundersnow/precondition.py
thundersnow/predicate.py
thundersnow/proxy.py
thundersnow/reflection.py
thundersnow/type.py
thundersnow/urlutil.py
thundersnow-0.0.9.dist-info/DESCRIPTION.rst
thundersnow-0.0.9.dist-info/METADATA
thundersnow-0.0.9.dist-info/RECORD
thundersnow-0.0.9.dist-info/WHEEL
thundersnow-0.0.9.dist-info/metadata.json
thundersnow-0.0.9.dist-info/namespace_packages.txt
thundersnow-0.0.9.dist-info/top_level.txt
thundersnow-0.0.9.dist-info/zip-safe
