Metadata-Version: 2.0
Name: thundersnow
Version: 0.0.9
Summary: ThuderSnow
Home-page: https://github.com/dillonhicks/thundersnows
Author: Dillon Hicks
Author-email: dillon@dillonhicks.io
License: Apache License Version 2.0
Platform: any
Classifier: Development Status :: 2 - Pre-Alpha
Classifier: Environment :: Web Environment
Classifier: Intended Audience :: Developers
Classifier: Operating System :: OS Independent
Classifier: Programming Language :: Python :: 2
Classifier: Programming Language :: Python :: 3
Classifier: Topic :: Internet :: WWW/HTTP :: Dynamic Content
Classifier: Topic :: Software Development :: Libraries :: Python Modules
Requires-Dist: boltons
Requires-Dist: scandir
Requires-Dist: pathlib2
Requires-Dist: cytoolz
Requires-Dist: six
Requires-Dist: typing
Requires-Dist: arrow
Requires-Dist: pytz
